drf_spectacular_websocket/__init__.py
drf_spectacular_websocket/apps.py
drf_spectacular_websocket/decorators.py
drf_spectacular_websocket/settings.py
drf_spectacular_websocket/types.py
drf_spectacular_websocket/schemas/__init__.py
drf_spectacular_websocket/schemas/consumer_schema.py
drf_spectacular_websocket/schemas/schema.py
drf_spectacular_websocket/templates/drf_spectacular/swagger_ui.js
drf_spectacular_websocket-1.3.1.dist-info/LICENSE
drf_spectacular_websocket-1.3.1.dist-info/METADATA
drf_spectacular_websocket-1.3.1.dist-info/WHEEL
drf_spectacular_websocket-1.3.1.dist-info/entry_points.txt
drf_spectacular_websocket-1.3.1.dist-info/top_level.txt
drf_spectacular_websocket-1.3.1.dist-info/RECORD
