Metadata-Version: 2.1
Name: drf_spectacular_websocket
Version: 1.3.1
Summary: Extend websocket schema decorator for Django Channels
Home-page: https://github.com/Friskes/drf-spectacular-websocket
Author: Friskes
Author-email: Friskes <friskesx@gmail.com>
License: MIT License
Project-URL: Homepage, https://github.com/Friskes/drf-spectacular-websocket
Project-URL: Changelog, https://github.com/Friskes/drf-spectacular-websocket/releases/
Project-URL: Issues, https://github.com/Friskes/drf-spectacular-websocket/issues
Keywords: Django,DRF,Spectacular,Swagger,Channels
Classifier: Development Status :: 5 - Production/Stable
Classifier: Environment :: Web Environment
Classifier: Intended Audience :: Developers
Classifier: Operating System :: OS Independent
Classifier: License :: OSI Approved :: MIT License
Classifier: Programming Language :: Python :: 3.8
Classifier: Programming Language :: Python :: 3.9
Classifier: Programming Language :: Python :: 3.10
Classifier: Programming Language :: Python :: 3.11
Classifier: Programming Language :: Python :: 3.12
Classifier: Framework :: Django :: 4.0
Classifier: Framework :: Django :: 4.1
Classifier: Framework :: Django :: 4.2
Classifier: Topic :: Internet :: WWW/HTTP
Classifier: Topic :: Documentation
Classifier: Topic :: Software Development :: Code Generators
Requires-Python: >=3.8
License-File: LICENSE
Requires-Dist: django>=4.0.0
Requires-Dist: djangorestframework>=3.14.0
Requires-Dist: drf-spectacular>=0.27.2
Requires-Dist: drf-spectacular-sidecar==2024.4.1
Requires-Dist: channels>=4.0.0
Provides-Extra: dev
Requires-Dist: pre-commit>=3.5.0; extra == "dev"
Requires-Dist: ruff==0.8.0; extra == "dev"
Requires-Dist: pytest>=7.0.1; extra == "dev"
Requires-Dist: mypy>=1.10.0; extra == "dev"
Requires-Dist: pytest-cov>=5.0.0; extra == "dev"
Requires-Dist: djangorestframework-simplejwt>=5.3.0; extra == "dev"
Requires-Dist: channels-auth-token-middlewares>=1.1.0; extra == "dev"
Provides-Extra: ci
Requires-Dist: ruff==0.8.0; extra == "ci"
Requires-Dist: pytest>=7.0.1; extra == "ci"
Requires-Dist: mypy>=1.10.0; extra == "ci"
Requires-Dist: pytest-cov>=5.0.0; extra == "ci"
Requires-Dist: djangorestframework-simplejwt>=5.3.0; extra == "ci"
Requires-Dist: channels-auth-token-middlewares>=1.1.0; extra == "ci"
